eurostat_deaths/__init__.py
eurostat_deaths/cache.py
eurostat_deaths/deaths.py
eurostat_deaths/populations.py
eurostat_deaths-0.2.0.dist-info/LICENSE
eurostat_deaths-0.2.0.dist-info/METADATA
eurostat_deaths-0.2.0.dist-info/WHEEL
eurostat_deaths-0.2.0.dist-info/top_level.txt
eurostat_deaths-0.2.0.dist-info/RECORD
