Metadata-Version: 2.1
Name: eurostat-deaths
Version: 0.2.0
Summary: Web Scraper for Eurostat data.
Home-page: https://github.com/martinbenes1996/eurostat_deaths
Author: Martin Beneš
Author-email: martinbenes1996@gmail.com
License: MIT
Download-URL: https://github.com/martinbenes1996/eurostat_deaths/archive/0.2.0.tar.gz
Keywords: eurostat,deaths,web,html,webscraping
Platform: UNKNOWN
Classifier: Development Status :: 4 - Beta
Classifier: Intended Audience :: Science/Research
Classifier: Intended Audience :: Developers
Classifier: Intended Audience :: Other Audience
Classifier: Environment :: Web Environment
Classifier: Topic :: Scientific/Engineering
Classifier: Topic :: Scientific/Engineering :: Information Analysis
Classifier: Topic :: Software Development :: Libraries
Classifier: Topic :: Utilities
Classifier: License :: OSI Approved :: MIT License
Classifier: Programming Language :: Python :: 3
Classifier: Programming Language :: Python :: 3.4
Classifier: Programming Language :: Python :: 3.5
Classifier: Programming Language :: Python :: 3.6
Requires-Dist: pandas
Requires-Dist: requests
